{
  "templates": [
    {
      "githubUrl": "hhttps://github.com/akveo/react-native-ui-kitten/tree/master/src/template-js",
      "npmPkg": "@ui-kitten/template-js",
      "ios": true,
      "android": true,
      "web": true,
      "expoGo": true,
      "github": {
        "urls": {
          "repo": "https://github.com/akveo/react-native-ui-kitten",
          "homepage": "https://github.com/akveo/react-native-ui-kitten#readme"
        },
        "stats": {
          "hasIssues": true,
          "hasWiki": false,
          "hasSponsorships": false,
          "hasDiscussions": true,
          "hasProjects": true,
          "hasVulnerabilityAlerts": false,
          "hasTopics": true,
          "updatedAt": "2023-04-26T16:13:33Z",
          "createdAt": "2016-12-20T08:22:38Z",
          "pushedAt": "2023-04-26T16:13:33Z",
          "forks": 949,
          "issues": 179,
          "subscribers": 119,
          "stars": 10675,
          "dependencies": 0
        },
        "name": "@ui-kitten/template-js",
        "fullName": "akveo/react-native-ui-kitten",
        "isPrivate": false,
        "description": "React Native template project with UI Kitten",
        "topics": [
          "ui-kitten",
          "template",
          "boilerplate"
        ],
        "license": {
          "name": "MIT License",
          "url": "http://choosealicense.com/licenses/mit/",
          "id": "MDc6TGljZW5zZTEz",
          "key": "mit",
          "spdxId": "MIT"
        },
        "hasTypes": false,
        "newArchitecture": false,
        "isArchived": false,
        "hasReadme": false,
        "hasNativeCode": false,
        "configPlugin": false
      },
      "unmaintained": true,
      "npm": {
        "downloads": 62,
        "weekDownloads": 12,
        "size": 241613,
        "versionsCount": 15,
        "latestRelease": "5.3.1",
        "latestReleaseDate": "2023-04-26T16:26:13.933Z",
        "hasReadme": false
      },
      "topicSearchString": "ui-kitten template boilerplate"
    },
    {
      "githubUrl": "https://github.com/akveo/react-native-ui-kitten/tree/master/src/template-ts",
      "npmPkg": "@ui-kitten/template-ts",
      "ios": true,
      "android": true,
      "web": true,
      "expoGo": true,
      "github": {
        "urls": {
          "repo": "https://github.com/akveo/react-native-ui-kitten",
          "homepage": "https://github.com/akveo/react-native-ui-kitten#readme"
        },
        "stats": {
          "hasIssues": true,
          "hasWiki": false,
          "hasSponsorships": false,
          "hasDiscussions": true,
          "hasProjects": true,
          "hasVulnerabilityAlerts": false,
          "hasTopics": true,
          "updatedAt": "2023-04-26T16:13:33Z",
          "createdAt": "2016-12-20T08:22:38Z",
          "pushedAt": "2023-04-26T16:13:33Z",
          "forks": 949,
          "issues": 179,
          "subscribers": 119,
          "stars": 10675,
          "dependencies": 0
        },
        "name": "@ui-kitten/template-ts",
        "fullName": "akveo/react-native-ui-kitten",
        "isPrivate": false,
        "description": "React Native template project with UI Kitten and TypeScript",
        "topics": [
          "ui-kitten",
          "template",
          "boilerplate"
        ],
        "license": {
          "name": "MIT License",
          "url": "http://choosealicense.com/licenses/mit/",
          "id": "MDc6TGljZW5zZTEz",
          "key": "mit",
          "spdxId": "MIT"
        },
        "hasTypes": false,
        "newArchitecture": false,
        "isArchived": false,
        "hasReadme": false,
        "hasNativeCode": false,
        "configPlugin": false
      },
      "unmaintained": true,
      "npm": {
        "downloads": 87,
        "weekDownloads": 4,
        "size": 241344,
        "versionsCount": 15,
        "latestRelease": "5.3.1",
        "latestReleaseDate": "2023-04-26T16:26:27.104Z",
        "hasReadme": false
      },
      "topicSearchString": "ui-kitten template boilerplate"
    },
    {
      "githubUrl": "https://github.com/react-native-community/react-native-template-typescript",
      "templateName": "react-native-template-typescript",
      "ios": true,
      "android": true,
      "github": {
        "urls": {
          "repo": "https://github.com/react-native-community/react-native-template-typescript",
          "homepage": "https://www.npmjs.com/package/react-native-template-typescript"
        },
        "stats": {
          "hasIssues": true,
          "hasWiki": false,
          "hasSponsorships": false,
          "hasDiscussions": false,
          "hasProjects": false,
          "hasVulnerabilityAlerts": false,
          "hasTopics": true,
          "updatedAt": "2023-06-26T15:21:55Z",
          "createdAt": "2018-03-05T19:15:51Z",
          "pushedAt": "2023-06-26T15:21:55Z",
          "forks": 365,
          "issues": 9,
          "subscribers": 39,
          "stars": 1897,
          "dependencies": 0
        },
        "name": "react-native-template-typescript",
        "fullName": "react-native-community/react-native-template-typescript",
        "isPrivate": false,
        "description": "👾 Clean and minimalist React Native template for a quick start with TypeScript.",
        "topics": [
          "typescript",
          "jest",
          "template",
          "boilerplate"
        ],
        "license": {
          "key": "mit",
          "name": "MIT License",
          "spdxId": "MIT",
          "url": "http://choosealicense.com/licenses/mit/",
          "id": "MDc6TGljZW5zZTEz"
        },
        "hasTypes": false,
        "newArchitecture": false,
        "isArchived": false,
        "hasReadme": true,
        "hasNativeCode": false,
        "configPlugin": false
      },
      "unmaintained": true,
      "npm": {},
      "topicSearchString": "typescript jest template boilerplate"
    },
    {
      "githubUrl": "https://github.com/gabimoncha/react-native-template",
      "templateName": "@gabimoncha/react-native-template",
      "ios": true,
      "android": true,
      "github": {
        "urls": {
          "repo": "https://github.com/gabimoncha/react-native-template",
          "homepage": "https://www.npmjs.com/package/@gabimoncha/react-native-template"
        },
        "stats": {
          "hasIssues": true,
          "hasWiki": true,
          "hasSponsorships": false,
          "hasDiscussions": false,
          "hasProjects": true,
          "hasVulnerabilityAlerts": false,
          "hasTopics": true,
          "updatedAt": "2022-05-24T08:12:32Z",
          "createdAt": "2021-01-14T15:33:47Z",
          "pushedAt": "2022-05-24T08:12:32Z",
          "forks": 22,
          "issues": 3,
          "subscribers": 5,
          "stars": 137,
          "dependencies": 0
        },
        "name": "@gabimoncha/react-native-template",
        "fullName": "gabimoncha/react-native-template",
        "isPrivate": false,
        "description": "An opinionated template to bootstrap your next React Native app with all the time-wasting packages you need to have.",
        "topics": [
          "typescript",
          "jest",
          "template",
          "boilerplate",
          "starter",
          "absolute",
          "imports",
          "navigation",
          "svg",
          "webview",
          "async",
          "storage",
          "styled",
          "components",
          "bundle",
          "visualiser",
          "husky",
          "git",
          "hooks",
          "startup",
          "time",
          "fast-image",
          "sentry",
          "authentication-flow",
          "push-notifications",
          "zustand",
          "query",
          "styled-components",
          "styled-system",
          "codepush",
          "detox",
          "netinfo",
          "filelogger"
        ],
        "license": {
          "key": "mit",
          "name": "MIT License",
          "spdxId": "MIT",
          "url": "http://choosealicense.com/licenses/mit/",
          "id": "MDc6TGljZW5zZTEz"
        },
        "hasTypes": false,
        "newArchitecture": false,
        "isArchived": true,
        "hasReadme": true,
        "hasNativeCode": false,
        "configPlugin": false
      },
      "unmaintained": true,
      "npm": {},
      "topicSearchString": "typescript jest template boilerplate starter absolute imports navigation svg webview async storage styled components bundle visualiser husky git hooks startup time fast-image sentry authentication-flow push-notifications zustand query styled-components styled-system codepush detox netinfo filelogger"
    },
    {
      "githubUrl": "https://github.com/LunatiqueCoder/luna/tree/master/packages/create-luna-app",
      "npmPkg": "create-luna-app",
      "ios": true,
      "android": true,
      "web": true,
      "dev": true,
      "github": {
        "urls": {
          "repo": "https://github.com/LunatiqueCoder/luna",
          "homepage": "https://github.com/LunatiqueCoder/luna/tree/master/packages/create-luna-app"
        },
        "stats": {
          "hasIssues": true,
          "hasWiki": true,
          "hasSponsorships": true,
          "hasDiscussions": true,
          "hasProjects": true,
          "hasVulnerabilityAlerts": true,
          "hasTopics": true,
          "updatedAt": "2023-04-10T20:58:11Z",
          "createdAt": "2021-09-01T10:32:43Z",
          "pushedAt": "2023-04-10T20:58:11Z",
          "forks": 19,
          "issues": 2,
          "subscribers": 5,
          "stars": 271,
          "dependencies": 1
        },
        "name": "create-luna-app",
        "fullName": "LunatiqueCoder/luna",
        "isPrivate": false,
        "description": "🌘Luna is a React Native and Next.js boilerplate so your app can run on Android, IOS and Web concurrently.",
        "topics": [
          "boilerplate",
          "template",
          "luna",
          "web",
          "next",
          "nextjs",
          "solito",
          "tamagui"
        ],
        "license": {
          "name": "MIT License",
          "url": "http://choosealicense.com/licenses/mit/",
          "id": "MDc6TGljZW5zZTEz",
          "key": "mit",
          "spdxId": "MIT"
        },
        "hasTypes": true,
        "newArchitecture": false,
        "isArchived": false,
        "hasReadme": true,
        "hasNativeCode": false,
        "configPlugin": false
      },
      "unmaintained": true,
      "npm": {
        "downloads": 13,
        "weekDownloads": 4,
        "size": 25567,
        "versionsCount": 18,
        "latestRelease": "3.0.3",
        "latestReleaseDate": "2023-04-10T20:58:26.600Z",
        "hasReadme": true
      },
      "topicSearchString": "boilerplate template luna web next nextjs solito tamagui"
    },
    {
      "githubUrl": "https://github.com/talknagish/react-native-turbo-starter",
      "ios": true,
      "android": true,
      "dev": true,
      "github": {
        "urls": {
          "repo": "https://github.com/talknagish/react-native-turbo-starter",
          "homepage": null
        },
        "stats": {
          "hasIssues": true,
          "hasWiki": false,
          "hasSponsorships": false,
          "hasDiscussions": false,
          "hasProjects": false,
          "hasVulnerabilityAlerts": true,
          "hasTopics": true,
          "updatedAt": "2022-04-29T07:16:29Z",
          "createdAt": "2022-04-16T09:53:09Z",
          "pushedAt": "2022-04-29T07:16:29Z",
          "forks": 25,
          "issues": 7,
          "subscribers": 9,
          "stars": 385,
          "dependencies": 0
        },
        "name": "react-native-turbo-starter",
        "fullName": "talknagish/react-native-turbo-starter",
        "isPrivate": false,
        "registry": "https://registry.npmjs.org/",
        "description": "React 0.68+ Turbo Module starter using codegen with typescript for Objective-C and Java/Kotlin with C++ shared library. 🚀🚀🚀",
        "topics": [
          "ios",
          "android"
        ],
        "license": {
          "key": "mit",
          "name": "MIT License",
          "spdxId": "MIT",
          "url": "http://choosealicense.com/licenses/mit/",
          "id": "MDc6TGljZW5zZTEz"
        },
        "hasTypes": true,
        "newArchitecture": true,
        "isArchived": false,
        "hasReadme": true,
        "hasNativeCode": true,
        "configPlugin": false
      },
      "unmaintained": true,
      "npm": {},
      "topicSearchString": "ios android"
    },
    {
      "githubUrl": "https://github.com/leotm/react-native-template-new-architecture",
      "ios": true,
      "android": true,
      "github": {
        "urls": {
          "repo": "https://github.com/leotm/react-native-template-new-architecture",
          "homepage": "https://reactnative.dev/blog/2022/06/16/resources-migrating-your-react-native-library-to-the-new-architecture#migration-status-of-popular-libraries"
        },
        "stats": {
          "hasIssues": true,
          "hasWiki": true,
          "hasSponsorships": true,
          "hasDiscussions": true,
          "hasProjects": true,
          "hasVulnerabilityAlerts": true,
          "hasTopics": true,
          "updatedAt": "2026-01-20T20:20:12Z",
          "createdAt": "2020-04-24T16:50:07Z",
          "pushedAt": "2026-01-20T20:20:12Z",
          "forks": 29,
          "issues": 31,
          "subscribers": 1,
          "stars": 263,
          "dependencies": 8
        },
        "name": "myapp",
        "fullName": "leotm/react-native-template-new-architecture",
        "isPrivate": true,
        "description": "React Native 0.83 ⚡ Hardened JS 🔒 LavaMoat 🌋 Ubuntu 24 🐧 macOS 26.3 Beta, Xcode 26.2 🍎 Hermes ⚙️ Fabric 🚅  Turbo Modules 💨 TS 5 ✅ Gradle 9, JDK 25, NDK 27 🤖 Ruby 3.4 💎 Yarn 4 📦 ESLint 🧹 Prettier ✨ Babel 🗼 ccache ♻️ Buck2 🚧 GHA ✔️ Node 20 ⬢ Storybook 6.5rc 📓 Renovate 🛠️ Socket ⚡ libs 📚 for curious early adopters :suspect: #RNEU #APPJS",
        "topics": [
          "typescript",
          "eslint",
          "prettier",
          "storybook",
          "arm64",
          "android",
          "ios",
          "gradle",
          "jest",
          "xcode",
          "ts-node",
          "deno",
          "fabric",
          "babel"
        ],
        "license": null,
        "hasTypes": false,
        "newArchitecture": false,
        "isArchived": false,
        "hasReadme": true,
        "hasNativeCode": true,
        "configPlugin": false
      },
      "npm": {},
      "topicSearchString": "typescript eslint prettier storybook arm64 android ios gradle jest xcode ts-node deno fabric babel"
    },
    {
      "githubUrl": "https://github.com/mmazzarolo/react-native-universal-monorepo",
      "ios": true,
      "android": true,
      "macos": true,
      "web": true,
      "windows": true,
      "github": {
        "urls": {
          "repo": "https://github.com/mmazzarolo/react-native-universal-monorepo",
          "homepage": null
        },
        "stats": {
          "hasIssues": true,
          "hasWiki": false,
          "hasSponsorships": false,
          "hasDiscussions": true,
          "hasProjects": false,
          "hasVulnerabilityAlerts": true,
          "hasTopics": true,
          "updatedAt": "2022-05-29T10:21:24Z",
          "createdAt": "2021-09-07T10:02:07Z",
          "pushedAt": "2022-05-29T10:21:24Z",
          "forks": 155,
          "issues": 16,
          "subscribers": 30,
          "stars": 1733,
          "dependencies": 0
        },
        "name": "react-native-universal-project",
        "fullName": "mmazzarolo/react-native-universal-monorepo",
        "isPrivate": true,
        "description": "React Native boilerplate supporting multiple platforms: Android, iOS, macOS, Windows, web, browser extensions, Electron.",
        "topics": [
          "electron",
          "web",
          "android",
          "ios",
          "windows",
          "macos"
        ],
        "license": {
          "key": "mit",
          "name": "MIT License",
          "spdxId": "MIT",
          "url": "http://choosealicense.com/licenses/mit/",
          "id": "MDc6TGljZW5zZTEz"
        },
        "hasTypes": false,
        "newArchitecture": false,
        "isArchived": false,
        "hasReadme": true,
        "hasNativeCode": false,
        "configPlugin": false
      },
      "unmaintained": true,
      "npm": {},
      "topicSearchString": "electron web android ios windows macos"
    },
    {
      "githubUrl": "https://github.com/Mindinventory/react-native-boilerplate",
      "npmPkg": "@mindinventory/react-native-boilerplate",
      "templateName": "@mindinventory/react-native-boilerplate",
      "ios": true,
      "android": true,
      "github": {
        "urls": {
          "repo": "https://github.com/Mindinventory/react-native-boilerplate",
          "homepage": "https://mindinventory.github.io/react-native-boilerplate/"
        },
        "stats": {
          "hasIssues": true,
          "hasWiki": true,
          "hasSponsorships": false,
          "hasDiscussions": true,
          "hasProjects": true,
          "hasVulnerabilityAlerts": false,
          "hasTopics": true,
          "updatedAt": "2024-12-09T12:24:41Z",
          "createdAt": "2022-04-26T09:26:18Z",
          "pushedAt": "2024-12-09T12:24:41Z",
          "forks": 22,
          "issues": 1,
          "subscribers": 5,
          "stars": 145,
          "dependencies": 9
        },
        "name": "@mindinventory/react-native-boilerplate",
        "fullName": "Mindinventory/react-native-boilerplate",
        "isPrivate": false,
        "description": "The Boilerplate contains all the basic packages, common components and, prebuilt code architecture. It will save developer's project setup time. supporting both expo and react-native CLI.",
        "topics": [
          "mindinventory",
          "boilerplate",
          "starter-kit",
          "template",
          "expo",
          "typescript",
          "boilerplate-template",
          "javascript",
          "starter-template",
          "typescript-boilerplate",
          "architecture"
        ],
        "license": {
          "key": "mit",
          "name": "MIT License",
          "spdxId": "MIT",
          "url": "http://choosealicense.com/licenses/mit/",
          "id": "MDc6TGljZW5zZTEz"
        },
        "hasTypes": false,
        "newArchitecture": false,
        "isArchived": false,
        "hasReadme": true,
        "hasNativeCode": false,
        "configPlugin": false
      },
      "npm": {
        "downloads": 209,
        "weekDownloads": 57,
        "size": 938452,
        "versionsCount": 19,
        "latestRelease": "3.0.0",
        "latestReleaseDate": "2024-12-09T12:31:11.082Z",
        "hasReadme": true
      },
      "topicSearchString": "mindinventory boilerplate starter-kit template expo typescript boilerplate-template javascript starter-template typescript-boilerplate architecture"
    },
    {
      "githubUrl": "https://github.com/ory/kratos-selfservice-ui-react-native",
      "images": [
        "https://www.ory.sh/docs/assets/images/1-78684ec591551f445a1064e274bf37b8.png"
      ],
      "ios": true,
      "android": true,
      "web": true,
      "expoGo": true,
      "github": {
        "urls": {
          "repo": "https://github.com/ory/kratos-selfservice-ui-react-native",
          "homepage": null
        },
        "stats": {
          "hasIssues": true,
          "hasWiki": false,
          "hasSponsorships": true,
          "hasDiscussions": false,
          "hasProjects": false,
          "hasVulnerabilityAlerts": false,
          "hasTopics": true,
          "updatedAt": "2026-01-28T21:40:53Z",
          "createdAt": "2020-08-03T09:32:56Z",
          "pushedAt": "2026-01-28T21:40:53Z",
          "forks": 33,
          "issues": 2,
          "subscribers": 10,
          "stars": 107,
          "dependencies": 40
        },
        "name": "@ory/expo-login-registration-template",
        "fullName": "ory/kratos-selfservice-ui-react-native",
        "isPrivate": false,
        "description": "A reference implementation of an app using ORY Kratos for auth (login), sign up (registration), profile settings (update password), MFA/2FA, account recovery (password reset), and more for React Native. This repository is available as an expo template!",
        "topics": [
          "ory-kratos",
          "registration",
          "login",
          "authentication",
          "auth",
          "ory"
        ],
        "license": {
          "key": "apache-2.0",
          "name": "Apache License 2.0",
          "spdxId": "Apache-2.0",
          "url": "http://choosealicense.com/licenses/apache-2.0/",
          "id": "MDc6TGljZW5zZTI="
        },
        "hasTypes": false,
        "newArchitecture": false,
        "isArchived": false,
        "hasReadme": true,
        "hasNativeCode": true,
        "configPlugin": false
      },
      "npm": {},
      "topicSearchString": "ory-kratos registration login authentication auth ory"
    },
    {
      "githubUrl": "https://github.com/tushu4212/rntemplate",
      "npmPkg": "@tushar4212/rntemplate",
      "ios": true,
      "android": true,
      "github": {
        "urls": {
          "repo": "https://github.com/tushu4212/rntemplate",
          "homepage": "https://github.com/tushu4212/rntemplate#readme"
        },
        "stats": {
          "hasIssues": true,
          "hasWiki": false,
          "hasSponsorships": false,
          "hasDiscussions": false,
          "hasProjects": true,
          "hasVulnerabilityAlerts": true,
          "hasTopics": true,
          "updatedAt": "2025-04-30T10:20:37Z",
          "createdAt": "2024-03-26T10:06:31Z",
          "pushedAt": "2025-04-30T10:20:37Z",
          "forks": 0,
          "issues": 0,
          "subscribers": 1,
          "stars": 1,
          "dependencies": 0
        },
        "name": "@tushar4212/rntemplate",
        "fullName": "tushu4212/rntemplate",
        "isPrivate": false,
        "description": "React native template ",
        "topics": [
          "boilerplate",
          "starter-kit",
          "template"
        ],
        "license": {
          "key": "mit",
          "name": "MIT License",
          "spdxId": "MIT",
          "url": "http://choosealicense.com/licenses/mit/",
          "id": "MDc6TGljZW5zZTEz"
        },
        "hasTypes": false,
        "newArchitecture": false,
        "isArchived": false,
        "hasReadme": true,
        "hasNativeCode": false,
        "configPlugin": false
      },
      "npm": {
        "downloads": 21,
        "weekDownloads": 1,
        "size": 649918,
        "versionsCount": 18,
        "latestRelease": "3.0.1",
        "latestReleaseDate": "2025-09-22T05:31:36.173Z",
        "hasReadme": true
      },
      "topicSearchString": "boilerplate starter-kit template"
    },
    {
      "githubUrl": "https://github.com/expo/expo/tree/main/templates/expo-template-default",
      "ios": true,
      "android": true,
      "web": true,
      "expoGo": true,
      "github": {
        "urls": {
          "repo": "https://github.com/expo/expo",
          "homepage": null
        },
        "stats": {
          "hasIssues": true,
          "hasWiki": true,
          "hasSponsorships": false,
          "hasDiscussions": true,
          "hasProjects": false,
          "hasVulnerabilityAlerts": true,
          "hasTopics": false,
          "updatedAt": "2026-01-29T21:17:04Z",
          "createdAt": "2016-08-15T17:14:25Z",
          "pushedAt": "2026-01-29T21:17:04Z",
          "forks": 10694,
          "issues": 360,
          "subscribers": 350,
          "stars": 46876,
          "dependencies": 26
        },
        "name": "expo-template-default",
        "fullName": "expo/expo",
        "isPrivate": false,
        "topics": [],
        "hasTypes": false,
        "newArchitecture": false,
        "isArchived": false,
        "hasReadme": true,
        "hasNativeCode": false,
        "configPlugin": false
      },
      "npm": {},
      "topicSearchString": ""
    },
    {
      "githubUrl": "https://github.com/expo/expo/tree/main/templates/expo-template-blank",
      "ios": true,
      "android": true,
      "expoGo": true,
      "github": {
        "urls": {
          "repo": "https://github.com/expo/expo",
          "homepage": null
        },
        "stats": {
          "hasIssues": true,
          "hasWiki": true,
          "hasSponsorships": false,
          "hasDiscussions": true,
          "hasProjects": false,
          "hasVulnerabilityAlerts": true,
          "hasTopics": false,
          "updatedAt": "2026-01-27T20:02:58Z",
          "createdAt": "2016-08-15T17:14:25Z",
          "pushedAt": "2026-01-27T20:02:58Z",
          "forks": 10694,
          "issues": 360,
          "subscribers": 350,
          "stars": 46876,
          "dependencies": 4
        },
        "name": "expo-template-blank",
        "fullName": "expo/expo",
        "isPrivate": false,
        "description": "The Blank project template includes the minimum dependencies to run and an empty root component.",
        "topics": [],
        "hasTypes": false,
        "newArchitecture": false,
        "isArchived": false,
        "hasReadme": false,
        "hasNativeCode": false,
        "configPlugin": false
      },
      "npm": {},
      "topicSearchString": ""
    },
    {
      "githubUrl": "https://github.com/expo/expo/tree/main/templates/expo-template-blank-typescript",
      "ios": true,
      "android": true,
      "expoGo": true,
      "github": {
        "urls": {
          "repo": "https://github.com/expo/expo",
          "homepage": null
        },
        "stats": {
          "hasIssues": true,
          "hasWiki": true,
          "hasSponsorships": false,
          "hasDiscussions": true,
          "hasProjects": false,
          "hasVulnerabilityAlerts": true,
          "hasTopics": false,
          "updatedAt": "2026-01-27T20:02:58Z",
          "createdAt": "2016-08-15T17:14:25Z",
          "pushedAt": "2026-01-27T20:02:58Z",
          "forks": 10694,
          "issues": 360,
          "subscribers": 350,
          "stars": 46876,
          "dependencies": 4
        },
        "name": "expo-template-blank-typescript",
        "fullName": "expo/expo",
        "isPrivate": false,
        "description": "The Blank project template includes the minimum dependencies to run and an empty root component.",
        "topics": [],
        "hasTypes": false,
        "newArchitecture": false,
        "isArchived": false,
        "hasReadme": false,
        "hasNativeCode": false,
        "configPlugin": false
      },
      "npm": {},
      "topicSearchString": ""
    },
    {
      "githubUrl": "https://github.com/expo/expo/tree/main/templates/expo-template-tabs",
      "ios": true,
      "android": true,
      "web": true,
      "expoGo": true,
      "github": {
        "urls": {
          "repo": "https://github.com/expo/expo",
          "homepage": null
        },
        "stats": {
          "hasIssues": true,
          "hasWiki": true,
          "hasSponsorships": false,
          "hasDiscussions": true,
          "hasProjects": false,
          "hasVulnerabilityAlerts": true,
          "hasTopics": false,
          "updatedAt": "2026-01-27T20:02:58Z",
          "createdAt": "2016-08-15T17:14:25Z",
          "pushedAt": "2026-01-27T20:02:58Z",
          "forks": 10694,
          "issues": 360,
          "subscribers": 350,
          "stars": 46876,
          "dependencies": 18
        },
        "name": "expo-template-tabs",
        "fullName": "expo/expo",
        "isPrivate": false,
        "description": "The Tab Navigation project template includes several example screens.",
        "topics": [],
        "hasTypes": false,
        "newArchitecture": false,
        "isArchived": false,
        "hasReadme": false,
        "hasNativeCode": false,
        "configPlugin": false
      },
      "npm": {},
      "topicSearchString": ""
    },
    {
      "githubUrl": "https://github.com/expo/expo/tree/main/templates/expo-template-bare-minimum",
      "ios": true,
      "android": true,
      "expoGo": true,
      "github": {
        "urls": {
          "repo": "https://github.com/expo/expo",
          "homepage": null
        },
        "stats": {
          "hasIssues": true,
          "hasWiki": true,
          "hasSponsorships": false,
          "hasDiscussions": true,
          "hasProjects": false,
          "hasVulnerabilityAlerts": true,
          "hasTopics": false,
          "updatedAt": "2026-01-28T12:14:22Z",
          "createdAt": "2016-08-15T17:14:25Z",
          "pushedAt": "2026-01-28T12:14:22Z",
          "forks": 10694,
          "issues": 360,
          "subscribers": 350,
          "stars": 46876,
          "dependencies": 4
        },
        "name": "expo-template-bare-minimum",
        "fullName": "expo/expo",
        "isPrivate": false,
        "description": "This bare project template includes a minimal setup for using unimodules with React Native.",
        "topics": [],
        "hasTypes": false,
        "newArchitecture": false,
        "isArchived": false,
        "hasReadme": false,
        "hasNativeCode": true,
        "configPlugin": false
      },
      "npm": {},
      "topicSearchString": ""
    }
  ],
  "topics": {
    "boilerplate": 7,
    "template": 7,
    "typescript": 4,
    "android": 3,
    "ios": 3,
    "jest": 3,
    "starter-kit": 2,
    "ui-kitten": 2,
    "web": 2,
    "absolute": 1,
    "architecture": 1,
    "arm64": 1,
    "async": 1,
    "auth": 1,
    "authentication": 1,
    "authentication-flow": 1,
    "babel": 1,
    "boilerplate-template": 1,
    "bundle": 1,
    "codepush": 1,
    "components": 1,
    "deno": 1,
    "detox": 1,
    "electron": 1,
    "eslint": 1,
    "expo": 1,
    "fabric": 1,
    "fast-image": 1,
    "filelogger": 1,
    "git": 1,
    "gradle": 1,
    "hooks": 1,
    "husky": 1,
    "imports": 1,
    "javascript": 1,
    "login": 1,
    "luna": 1,
    "macos": 1,
    "mindinventory": 1,
    "navigation": 1,
    "netinfo": 1,
    "next": 1,
    "nextjs": 1,
    "ory": 1,
    "ory-kratos": 1,
    "prettier": 1,
    "push-notifications": 1,
    "query": 1,
    "registration": 1,
    "sentry": 1,
    "solito": 1,
    "starter": 1,
    "starter-template": 1,
    "startup": 1,
    "storage": 1,
    "storybook": 1,
    "styled": 1,
    "styled-components": 1,
    "styled-system": 1,
    "svg": 1,
    "tamagui": 1,
    "time": 1,
    "ts-node": 1,
    "typescript-boilerplate": 1,
    "visualiser": 1,
    "webview": 1,
    "windows": 1,
    "xcode": 1,
    "zustand": 1
  }
}